marlindb/Connection.py
marlindb/Database.py
marlindb/Table.py
marlindb/__init__.py
marlindb-0.1.0.3.dist-info/METADATA
marlindb-0.1.0.3.dist-info/RECORD
marlindb-0.1.0.3.dist-info/WHEEL
marlindb-0.1.0.3.dist-info/top_level.txt
