Metadata-Version: 2.1
Name: marlindb
Version: 0.1.0.3
Summary: Python interface for MarlinDB
Home-page: http://www.datainz.com
Author: DataInz Technologies Pvt. Ltd.
Author-email: johnspaul92@gmail.com
License: Proprietary License
Platform: UNKNOWN
